Metadata-Version: 2.1
Name: kripa-sindhu-resume
Version: 0.0.3
Summary: A very own private resume
Home-page: 
Author: Kripa Sindhu
Author-email: sindhukripa007@gmail.com
License: MIT
Keywords: currency_convertor
Classifier: Development Status :: 5 - Production/Stable
Classifier: Intended Audience :: Education
Classifier: Operating System :: Microsoft :: Windows :: Windows 10
Classifier: License :: OSI Approved :: MIT License
Classifier: Programming Language :: Python :: 3
License-File: LICENCE.txt
